unixtimestampfield/__init__.py
unixtimestampfield/admin.py
unixtimestampfield/fields.py
unixtimestampfield/models.py
unixtimestampfield/submiddleware.py
unixtimestampfield/tests.py
unixtimestampfield/views.py
unixtimestampfield/templatetags/__init__.py
unixtimestampfield/templatetags/unixtimestampfield.py
django_unixtimestampfield-0.5.0.dist-info/LICENSE
django_unixtimestampfield-0.5.0.dist-info/METADATA
django_unixtimestampfield-0.5.0.dist-info/WHEEL
django_unixtimestampfield-0.5.0.dist-info/top_level.txt
django_unixtimestampfield-0.5.0.dist-info/RECORD
