Metadata-Version: 2.1
Name: django-unixtimestampfield
Version: 0.5.0
Summary: Django Unix timestamp (POSIX type) field
Home-page: https://github.com/myyang/django-unixtimestampfield
Author: Garfield.Yang
Author-email: ymy1019@gmail.com
License: MIT
Platform: UNKNOWN
Classifier: Development Status :: 4 - Beta
Classifier: License :: OSI Approved :: MIT License
Classifier: Intended Audience :: Developers
Classifier: Programming Language :: Python
Classifier: Framework :: Django
License-File: LICENSE
